RandomListOrDictGenerator/__init__.py
RandomListOrDictGenerator/list_or_dict_generator.py
RandomListOrDictGenerator-1.0.0.dist-info/METADATA
RandomListOrDictGenerator-1.0.0.dist-info/WHEEL
RandomListOrDictGenerator-1.0.0.dist-info/top_level.txt
RandomListOrDictGenerator-1.0.0.dist-info/RECORD
