Metadata-Version: 2.1
Name: RandomListOrDictGenerator
Version: 1.0.0
Summary: Generate random list/dictionary
Author: Serge Eric KALAGA
Author-email: kalagaserge4@gmail.com
Keywords: python,list,dictionnary,generator,string
Classifier: Development Status :: 1 - Planning
Classifier: Intended Audience :: Developers
Classifier: Programming Language :: Python :: 3
Classifier: Operating System :: Unix
Classifier: Operating System :: MacOS :: MacOS X
Classifier: Operating System :: Microsoft :: Windows
